aiwand/__init__.py
aiwand/classifier.py
aiwand/cli.py
aiwand/config.py
aiwand/core.py
aiwand/extract.py
aiwand/helper.py
aiwand/models.py
aiwand/preferences.py
aiwand/prompts.py
aiwand/setup.py
aiwand/utils/__init__.py
aiwand/utils/extras.py
aiwand/utils/file_utils.py
aiwand/utils/funcs.py
aiwand/utils/gemini_utils.py
aiwand/utils/llm_utils.py
aiwand/utils/openai_llm_utils.py
aiwand/utils/web_utils.py
aiwand-0.4.34.dist-info/licenses/LICENSE
aiwand-0.4.34.dist-info/METADATA
aiwand-0.4.34.dist-info/WHEEL
aiwand-0.4.34.dist-info/entry_points.txt
aiwand-0.4.34.dist-info/top_level.txt
aiwand-0.4.34.dist-info/RECORD
