Metadata-Version: 2.4
Name: aiwand
Version: 0.4.34
Summary: A simple AI toolkit for text processing using OpenAI and Gemini APIs
Home-page: https://github.com/onlyoneaman/aiwand
Author: Aman Kumar
Author-email: 2000.aman.sinha@gmail.com
Keywords: aiwand,ai,wand,ai wand,ai toolkit,openai,gemini,llm,pydantic,provider switching,structured output,text processing,call_ai,extract,summarization,chat,generate,classification
Classifier: Development Status :: 3 - Alpha
Classifier: Intended Audience :: Developers
Classifier: License :: OSI Approved :: MIT License
Classifier: Operating System :: OS Independent
Classifier: Programming Language :: Python :: 3
Classifier: Programming Language :: Python :: 3.8
Classifier: Programming Language :: Python :: 3.9
Classifier: Programming Language :: Python :: 3.10
Classifier: Programming Language :: Python :: 3.11
Classifier: Programming Language :: Python :: 3.12
Requires-Python: >=3.8
License-File: LICENSE
Requires-Dist: openai>=1.0.0
Requires-Dist: python-dotenv>=0.19.0
Requires-Dist: beautifulsoup4>=4.0
Requires-Dist: google-genai>=1.20.0
Provides-Extra: dev
Requires-Dist: pytest>=6.0; extra == "dev"
Requires-Dist: black>=21.0; extra == "dev"
Requires-Dist: flake8>=3.8; extra == "dev"
Dynamic: author
Dynamic: author-email
Dynamic: classifier
Dynamic: description
Dynamic: description-content-type
Dynamic: home-page
Dynamic: keywords
Dynamic: license-file
Dynamic: provides-extra
Dynamic: requires-dist
Dynamic: requires-python
Dynamic: summary
